furst_optics/__init__.py
furst_optics-0.0.0.dist-info/METADATA
furst_optics-0.0.0.dist-info/WHEEL
furst_optics-0.0.0.dist-info/top_level.txt
furst_optics-0.0.0.dist-info/RECORD
