Metadata-Version: 2.1
Name: furst-optics
Version: 0.0.0
Summary: A model of the optical design for the Full-sun Ultraviolet Rocket Spectrometer (FURST).
Author-email: "Roy T. Smart" <roytsmart@gmail.com>
Project-URL: Homepage, https://github.com/Kankelborg-Group/furst-optics
Project-URL: Documentation, https://furst-optics.readthedocs.io/en/latest
Classifier: Programming Language :: Python :: 3
Requires-Python: >=3.10
Requires-Dist: astropy
Requires-Dist: optika ==0.3.1
Provides-Extra: doc
Requires-Dist: pytest ; extra == 'doc'
Requires-Dist: matplotlib ; extra == 'doc'
Requires-Dist: graphviz ; extra == 'doc'
Requires-Dist: sphinx-autodoc-typehints ; extra == 'doc'
Requires-Dist: sphinxcontrib-bibtex ; extra == 'doc'
Requires-Dist: pydata-sphinx-theme ; extra == 'doc'
Requires-Dist: ipykernel ; extra == 'doc'
Requires-Dist: jupyter-sphinx ; extra == 'doc'
Requires-Dist: sphinx-favicon ; extra == 'doc'
Provides-Extra: test
Requires-Dist: pytest ; extra == 'test'
